rex.py
rexbox.py
rext.py
rexy.py
rext-0.1.24.dist-info/LICENSE
rext-0.1.24.dist-info/METADATA
rext-0.1.24.dist-info/WHEEL
rext-0.1.24.dist-info/top_level.txt
rext-0.1.24.dist-info/RECORD
