Metadata-Version: 2.1
Name: rext
Version: 0.1.24
Summary: A toolbox by Rex
Home-page: https://github.com/FallingHeart/rext
Author: rex nathan
Author-email: ceo@bamo.tech
License: MIT
Platform: UNKNOWN
Classifier: License :: OSI Approved :: MIT License
Classifier: Programming Language :: Python
Classifier: Programming Language :: Python :: 3
Classifier: Programming Language :: Python :: 3.6
Classifier: Programming Language :: Python :: Implementation :: CPython
Classifier: Programming Language :: Python :: Implementation :: PyPy
Requires-Python: >=3.6.0
License-File: LICENSE
Requires-Dist: pymongo
Requires-Dist: pandas
Requires-Dist: requests
